CrudeBHT/__init__.py
CrudeBHT/__main__.py
CrudeBHT/bhtree.py
CrudeBHT/body.py
CrudeBHT/example.py
CrudeBHT/quadrant.py
CrudeBHT/rendering.py
CrudeBHT/simulation.py
CrudeBHT/system.py
code/__init__.py
code/bhtree.py
code/body.py
code/example.py
code/quadrant.py
code/rendering.py
code/simulation.py
code/system.py
CrudeBHT-1.0.7.dist-info/LICENSE
CrudeBHT-1.0.7.dist-info/METADATA
CrudeBHT-1.0.7.dist-info/WHEEL
CrudeBHT-1.0.7.dist-info/entry_points.txt
CrudeBHT-1.0.7.dist-info/top_level.txt
CrudeBHT-1.0.7.dist-info/RECORD
