Metadata-Version: 2.1
Name: CrudeBHT
Version: 1.0.7
Summary: A simple implementation of the Barnes-Hut algorithm for N-body simulations in python 3.7 
Home-page: UNKNOWN
Author: Naimish Mani B
Author-email: naimish240@gmail.com
License: UNKNOWN
Platform: UNKNOWN
Classifier: Programming Language :: Python :: 3
Classifier: License :: OSI Approved :: MIT License
Classifier: Operating System :: OS Independent
